[
  {
    "label": "cathedral-amber",
    "oracle_class": "cathedral-clear",
    "seed": 43,
    "design": "oracle",
    "n_lightings": 4,
    "n_pairs": 6,
    "invariance_T": 0.1996145247393224,
    "invariance_h": 0.005510975611159073,
    "gt_T_mae": 0.14591624794532804,
    "gt_h_mae": 0.08764488650124638
  },
  {
    "label": "cathedral-amber",
    "oracle_class": "cathedral-clear",
    "seed": 43,
    "design": "continuous",
    "n_lightings": 4,
    "n_pairs": 6,
    "invariance_T": 0.15253954391000463,
    "invariance_h": 0.29373729074622307,
    "gt_T_mae": 0.21396570108302854,
    "gt_h_mae": 0.21254674557304465
  },
  {
    "label": "cathedral-amber",
    "oracle_class": "cathedral-clear",
    "seed": 43,
    "design": "continuous_persheet",
    "n_lightings": 4,
    "n_pairs": 6,
    "invariance_T": 0.15253954391000463,
    "invariance_h": 0.29373729074622307,
    "gt_T_mae": 0.21396570108302854,
    "gt_h_mae": 0.21254674557304465
  },
  {
    "label": "cathedral-green",
    "oracle_class": "cathedral-clear",
    "seed": 42,
    "design": "oracle",
    "n_lightings": 4,
    "n_pairs": 6,
    "invariance_T": 0.17717874090551292,
    "invariance_h": 0.007268983528187742,
    "gt_T_mae": 0.1444652551309919,
    "gt_h_mae": 0.08355730440432492
  },
  {
    "label": "cathedral-green",
    "oracle_class": "cathedral-clear",
    "seed": 42,
    "design": "continuous",
    "n_lightings": 4,
    "n_pairs": 6,
    "invariance_T": 0.14658468175656134,
    "invariance_h": 0.24608259519093234,
    "gt_T_mae": 0.24556222848193837,
    "gt_h_mae": 0.19198928101971963
  },
  {
    "label": "cathedral-green",
    "oracle_class": "cathedral-clear",
    "seed": 42,
    "design": "continuous_persheet",
    "n_lightings": 4,
    "n_pairs": 6,
    "invariance_T": 0.13148280729215214,
    "invariance_h": 0.24608259519093234,
    "gt_T_mae": 0.2689162769923843,
    "gt_h_mae": 0.19198928101971963
  },
  {
    "label": "dark-deep",
    "oracle_class": "dark-opaque",
    "seed": 501,
    "design": "oracle",
    "n_lightings": 3,
    "n_pairs": 3,
    "invariance_T": 0.025973940186658624,
    "invariance_h": 0.08797129027276956,
    "gt_T_mae": 0.11143822467694459,
    "gt_h_mae": 0.14307494749905456
  },
  {
    "label": "dark-deep",
    "oracle_class": "dark-opaque",
    "seed": 501,
    "design": "continuous",
    "n_lightings": 3,
    "n_pairs": 3,
    "invariance_T": 0.018505276465649135,
    "invariance_h": 0.11353353289319346,
    "gt_T_mae": 0.04422693342138004,
    "gt_h_mae": 0.332073133912864
  },
  {
    "label": "dark-deep",
    "oracle_class": "dark-opaque",
    "seed": 501,
    "design": "continuous_persheet",
    "n_lightings": 3,
    "n_pairs": 3,
    "invariance_T": 0.009706043951873591,
    "invariance_h": 0.11353353289319346,
    "gt_T_mae": 0.03938700818647207,
    "gt_h_mae": 0.332073133912864
  },
  {
    "label": "dark-opaque",
    "oracle_class": "dark-opaque",
    "seed": 44,
    "design": "oracle",
    "n_lightings": 4,
    "n_pairs": 6,
    "invariance_T": 0.05682616337915588,
    "invariance_h": 0.16297090182034732,
    "gt_T_mae": 0.07119879637632105,
    "gt_h_mae": 0.23038001962246063
  },
  {
    "label": "dark-opaque",
    "oracle_class": "dark-opaque",
    "seed": 44,
    "design": "continuous",
    "n_lightings": 4,
    "n_pairs": 6,
    "invariance_T": 0.35138875197013797,
    "invariance_h": 0.33381106847241065,
    "gt_T_mae": 0.2640757166745691,
    "gt_h_mae": 0.32245160107577975
  },
  {
    "label": "dark-opaque",
    "oracle_class": "dark-opaque",
    "seed": 44,
    "design": "continuous_persheet",
    "n_lightings": 4,
    "n_pairs": 6,
    "invariance_T": 0.05822506495846003,
    "invariance_h": 0.33381106847241065,
    "gt_T_mae": 0.21419896637685049,
    "gt_h_mae": 0.32245160107577975
  },
  {
    "label": "dark-opaque",
    "oracle_class": "dark-opaque",
    "seed": 47,
    "design": "oracle",
    "n_lightings": 6,
    "n_pairs": 15,
    "invariance_T": 0.027006534440129668,
    "invariance_h": 0.060920376141674046,
    "gt_T_mae": 0.04932162912611221,
    "gt_h_mae": 0.22945751403326878
  },
  {
    "label": "dark-opaque",
    "oracle_class": "dark-opaque",
    "seed": 47,
    "design": "continuous",
    "n_lightings": 6,
    "n_pairs": 15,
    "invariance_T": 0.23139217193930062,
    "invariance_h": 0.3115797813707321,
    "gt_T_mae": 0.1581049373927361,
    "gt_h_mae": 0.2583741365025841
  },
  {
    "label": "dark-opaque",
    "oracle_class": "dark-opaque",
    "seed": 47,
    "design": "continuous_persheet",
    "n_lightings": 6,
    "n_pairs": 15,
    "invariance_T": 0.03943220770373268,
    "invariance_h": 0.3115797813707321,
    "gt_T_mae": 0.06235558005514697,
    "gt_h_mae": 0.2583741365025841
  },
  {
    "label": "dark-ruby",
    "oracle_class": "dark-opaque",
    "seed": 502,
    "design": "oracle",
    "n_lightings": 3,
    "n_pairs": 3,
    "invariance_T": 0.023028468152658174,
    "invariance_h": 0.03521288980484997,
    "gt_T_mae": 0.06083342757818053,
    "gt_h_mae": 0.21488573782283027
  },
  {
    "label": "dark-ruby",
    "oracle_class": "dark-opaque",
    "seed": 502,
    "design": "continuous",
    "n_lightings": 3,
    "n_pairs": 3,
    "invariance_T": 0.09189943706388289,
    "invariance_h": 0.2505698716674422,
    "gt_T_mae": 0.11641789544818794,
    "gt_h_mae": 0.24699118579070137
  },
  {
    "label": "dark-ruby",
    "oracle_class": "dark-opaque",
    "seed": 502,
    "design": "continuous_persheet",
    "n_lightings": 3,
    "n_pairs": 3,
    "invariance_T": 0.030167058036010913,
    "invariance_h": 0.2505698716674422,
    "gt_T_mae": 0.08880173345932207,
    "gt_h_mae": 0.24699118579070137
  },
  {
    "label": "dark-slate",
    "oracle_class": "dark-opaque",
    "seed": 503,
    "design": "oracle",
    "n_lightings": 3,
    "n_pairs": 3,
    "invariance_T": 0.05850904733130954,
    "invariance_h": 0.10353663090601802,
    "gt_T_mae": 0.1524850315250517,
    "gt_h_mae": 0.09010534951465998
  },
  {
    "label": "dark-slate",
    "oracle_class": "dark-opaque",
    "seed": 503,
    "design": "continuous",
    "n_lightings": 3,
    "n_pairs": 3,
    "invariance_T": 0.2753457473825907,
    "invariance_h": 0.25970109956211823,
    "gt_T_mae": 0.1493597674534696,
    "gt_h_mae": 0.42691589879798314
  },
  {
    "label": "dark-slate",
    "oracle_class": "dark-opaque",
    "seed": 503,
    "design": "continuous_persheet",
    "n_lightings": 3,
    "n_pairs": 3,
    "invariance_T": 0.04024106263311134,
    "invariance_h": 0.25970109956211823,
    "gt_T_mae": 0.04477058168861838,
    "gt_h_mae": 0.42691589879798314
  },
  {
    "label": "streaky-mix",
    "oracle_class": "wispy",
    "seed": 45,
    "design": "oracle",
    "n_lightings": 4,
    "n_pairs": 6,
    "invariance_T": 0.1177142528077108,
    "invariance_h": 0.47391647132908793,
    "gt_T_mae": 0.1363617508196171,
    "gt_h_mae": 0.414408642714766
  },
  {
    "label": "streaky-mix",
    "oracle_class": "wispy",
    "seed": 45,
    "design": "continuous",
    "n_lightings": 4,
    "n_pairs": 6,
    "invariance_T": 0.20335006220941673,
    "invariance_h": 0.47391647132908793,
    "gt_T_mae": 0.17814610157534833,
    "gt_h_mae": 0.414408642714766
  },
  {
    "label": "streaky-mix",
    "oracle_class": "wispy",
    "seed": 45,
    "design": "continuous_persheet",
    "n_lightings": 4,
    "n_pairs": 6,
    "invariance_T": 0.1177142528077108,
    "invariance_h": 0.47391647132908793,
    "gt_T_mae": 0.1363617508196171,
    "gt_h_mae": 0.414408642714766
  },
  {
    "label": "wispy-white",
    "oracle_class": "wispy",
    "seed": 46,
    "design": "oracle",
    "n_lightings": 4,
    "n_pairs": 6,
    "invariance_T": 0.11652585708290357,
    "invariance_h": 0.1182719228012925,
    "gt_T_mae": 0.12190643498855153,
    "gt_h_mae": 0.13711361445586326
  },
  {
    "label": "wispy-white",
    "oracle_class": "wispy",
    "seed": 46,
    "design": "continuous",
    "n_lightings": 4,
    "n_pairs": 6,
    "invariance_T": 0.11652585708290357,
    "invariance_h": 0.1182719228012925,
    "gt_T_mae": 0.12190643498855153,
    "gt_h_mae": 0.13711361445586326
  },
  {
    "label": "wispy-white",
    "oracle_class": "wispy",
    "seed": 46,
    "design": "continuous_persheet",
    "n_lightings": 4,
    "n_pairs": 6,
    "invariance_T": 0.11652585708290357,
    "invariance_h": 0.1182719228012925,
    "gt_T_mae": 0.12190643498855153,
    "gt_h_mae": 0.13711361445586326
  }
]